LICENSE
MANIFEST.in
README
setup.py
version.py
rask_njord_mongodb/__init__.py
rask_njord_mongodb/codec.py
rask_njord_mongodb.egg-info/PKG-INFO
rask_njord_mongodb.egg-info/SOURCES.txt
rask_njord_mongodb.egg-info/dependency_links.txt
rask_njord_mongodb.egg-info/requires.txt
rask_njord_mongodb.egg-info/top_level.txt
rask_njord_mongodb/cursor/__init__.py