Metadata-Version: 1.0
Name: rask-njord-mongodb
Version: 1.0.0
Summary: Rask Mongodb Connector
Home-page: https://gitlab.com/vikingmakt/rask_njord_mongodb
Author: Umgeher Torgersen
Author-email: me@umgeher.org
License: https://gitlab.com/vikingmakt/rask_njord_mongodb/raw/master/LICENSE
Platform: UNKNOWN
